examples/basic_example.py
tests/test_basics.py
zymp/__init__.py
zymp/plotting.py
zymp/stacked_sites_array.py
zymp/tools.py
zymp/version.py
zymp-0.1.4.dist-info/licenses/LICENCE.txt
zymp-0.1.4.dist-info/METADATA
zymp-0.1.4.dist-info/WHEEL
zymp-0.1.4.dist-info/top_level.txt
zymp-0.1.4.dist-info/RECORD
