Metadata-Version: 2.4
Name: zymp
Version: 0.1.4
Summary: Design compact sequences with many enzyme restriction sites.
Author: Zulko
License-Expression: MIT
Project-URL: Homepage, https://github.com/Edinburgh-Genome-Foundry/zymp
Keywords: DNA,sequence,design,restriction,site,array
License-File: LICENCE.txt
Requires-Dist: numpy
Requires-Dist: dnachisel
Requires-Dist: dna_features_viewer
Requires-Dist: biopython
Requires-Dist: proglog
Dynamic: license-file
